{"v":"5.4.4","fr":25,"ip":0,"op":53,"w":680,"h":680,"nm":"我的 个人视角 完整 2","ddd":0,"assets":[{"id":"image_0","w":12,"h":12,"u":"images/","p":"img_0.png","e":0},{"id":"image_1","w":18,"h":18,"u":"images/","p":"img_1.png","e":0},{"id":"image_2","w":18,"h":18,"u":"images/","p":"img_2.png","e":0},{"id":"image_3","w":268,"h":268,"u":"images/","p":"img_3.png","e":0},{"id":"image_4","w":316,"h":316,"u":"images/","p":"img_4.png","e":0},{"id":"image_5","w":364,"h":364,"u":"images/","p":"img_5.png","e":0},{"id":"image_6","w":412,"h":412,"u":"images/","p":"img_6.png","e":0},{"id":"image_7","w":464,"h":464,"u":"images/","p":"img_7.png","e":0},{"id":"comp_0","layers":[{"ddd":0,"ind":1,"ty":2,"nm":"右上椭圆形.png","cl":"png","parent":11,"refId":"image_0","sr":1,"ks":{"o":{"a":1,"k":[{"i":{"x":[0.833],"y":[0.833]},"o":{"x":[0.167],"y":[0.167]},"t":18,"s":[100],"e":[4]},{"t":54}],"ix":11},"r":{"a":1,"k":[{"i":{"x":[0.833],"y":[0.833]},"o":{"x":[0.167],"y":[0.167]},"t":0,"s":[0],"e":[183.462]},{"t":53}],"ix":10},"p":{"a":0,"k":[230,232,0],"ix":2},"a":{"a":0,"k":[-215.761,226.333,0],"ix":1},"s":{"a":0,"k":[73.807,74.257,100],"ix":6}},"ao":0,"ip":0,"op":53,"st":0,"bm":0},{"ddd":0,"ind":2,"ty":2,"nm":"中间椭圆形.png","cl":"png","parent":8,"refId":"image_1","sr":1,"ks":{"o":{"a":1,"k":[{"i":{"x":[0.833],"y":[0.833]},"o":{"x":[0.167],"y":[0.167]},"t":12,"s":[100],"e":[22]},{"t":50}],"ix":11},"r":{"a":1,"k":[{"i":{"x":[0.833],"y":[0.833]},"o":{"x":[0.167],"y":[0.167]},"t":0,"s":[0],"e":[212]},{"t":53}],"ix":10},"p":{"a":0,"k":[230,232,0],"ix":2},"a":{"a":0,"k":[-46.787,235,0],"ix":1},"s":{"a":0,"k":[98.684,98.684,100],"ix":6}},"ao":0,"ip":0,"op":53,"st":0,"bm":0},{"ddd":0,"ind":3,"ty":2,"nm":"左上椭圆形.png","cl":"png","parent":12,"refId":"image_2","sr":1,"ks":{"o":{"a":1,"k":[{"i":{"x":[0.833],"y":[0.833]},"o":{"x":[0.167],"y":[0.167]},"t":20,"s":[100],"e":[0]},{"t":54}],"ix":11},"r":{"a":1,"k":[{"i":{"x":[0.833],"y":[0.833]},"o":{"x":[0.167],"y":[0.167]},"t":0,"s":[0],"e":[183.462]},{"t":53}],"ix":10},"p":{"a":0,"k":[232,232,0],"ix":2},"a":{"a":0,"k":[83.453,334.333,0],"ix":1},"s":{"a":0,"k":[68.807,68.807,100],"ix":6}},"ao":0,"ip":0,"op":53,"st":0,"bm":0},{"ddd":0,"ind":4,"ty":2,"nm":"3.png","cl":"png","refId":"image_3","sr":1,"ks":{"o":{"a":1,"k":[{"i":{"x":[0.833],"y":[0.833]},"o":{"x":[0.167],"y":[0.167]},"t":4,"s":[100],"e":[0]},{"t":42}],"ix":11},"r":{"a":0,"k":0,"ix":10},"p":{"a":0,"k":[373,371.5,0],"ix":2},"a":{"a":0,"k":[134,134,0],"ix":1},"s":{"a":1,"k":[{"i":{"x":[0.667,0.667,0.667],"y":[1,1,1]},"o":{"x":[0.333,0.333,0.333],"y":[0,0,0]},"t":4,"s":[76,76,100],"e":[100,100,100]},{"t":42}],"ix":6}},"ao":0,"ip":0,"op":53,"st":0,"bm":0},{"ddd":0,"ind":5,"ty":2,"nm":"4.png","cl":"png","refId":"image_4","sr":1,"ks":{"o":{"a":1,"k":[{"i":{"x":[0.833],"y":[0.833]},"o":{"x":[0.167],"y":[0.167]},"t":6,"s":[100],"e":[0]},{"t":44}],"ix":11},"r":{"a":0,"k":0,"ix":10},"p":{"a":0,"k":[373,371.5,0],"ix":2},"a":{"a":0,"k":[158,158,0],"ix":1},"s":{"a":1,"k":[{"i":{"x":[0.667,0.667,0.667],"y":[1,1,1]},"o":{"x":[0.333,0.333,0.333],"y":[0,0,0]},"t":6,"s":[76,76,100],"e":[100,100,100]},{"t":44}],"ix":6}},"ao":0,"ip":0,"op":53,"st":0,"bm":0},{"ddd":0,"ind":6,"ty":2,"nm":"5.png","cl":"png","refId":"image_5","sr":1,"ks":{"o":{"a":1,"k":[{"i":{"x":[0.833],"y":[0.833]},"o":{"x":[0.167],"y":[0.167]},"t":8,"s":[100],"e":[0]},{"t":46}],"ix":11},"r":{"a":0,"k":0,"ix":10},"p":{"a":0,"k":[373,371.5,0],"ix":2},"a":{"a":0,"k":[182,182,0],"ix":1},"s":{"a":1,"k":[{"i":{"x":[0.667,0.667,0.667],"y":[1,1,1]},"o":{"x":[0.333,0.333,0.333],"y":[0,0,0]},"t":8,"s":[76,76,100],"e":[100,100,100]},{"t":46}],"ix":6}},"ao":0,"ip":0,"op":53,"st":0,"bm":0},{"ddd":0,"ind":7,"ty":2,"nm":"6.png","cl":"png","refId":"image_6","sr":1,"ks":{"o":{"a":1,"k":[{"i":{"x":[0.833],"y":[0.833]},"o":{"x":[0.167],"y":[0.167]},"t":10,"s":[100],"e":[0]},{"t":48}],"ix":11},"r":{"a":0,"k":0,"ix":10},"p":{"a":0,"k":[373,371.5,0],"ix":2},"a":{"a":0,"k":[206,206,0],"ix":1},"s":{"a":1,"k":[{"i":{"x":[0.667,0.667,0.667],"y":[1,1,1]},"o":{"x":[0.333,0.333,0.333],"y":[0,0,0]},"t":10,"s":[76,76,100],"e":[100,100,100]},{"t":48}],"ix":6}},"ao":0,"ip":0,"op":53,"st":0,"bm":0},{"ddd":0,"ind":8,"ty":2,"nm":"7.png","cl":"png","refId":"image_7","sr":1,"ks":{"o":{"a":1,"k":[{"i":{"x":[0.833],"y":[0.833]},"o":{"x":[0.167],"y":[0.167]},"t":12,"s":[100],"e":[22]},{"t":50}],"ix":11},"r":{"a":0,"k":0,"ix":10},"p":{"a":0,"k":[372.5,371.5,0],"ix":2},"a":{"a":0,"k":[230,232,0],"ix":1},"s":{"a":1,"k":[{"i":{"x":[0.667,0.667,0.667],"y":[1,1,1]},"o":{"x":[0.333,0.333,0.333],"y":[0,0,0]},"t":12,"s":[76,76,100],"e":[100,100,100]},{"t":50}],"ix":6}},"ao":0,"ip":0,"op":53,"st":0,"bm":0},{"ddd":0,"ind":9,"ty":2,"nm":"8","refId":"image_7","sr":1,"ks":{"o":{"a":1,"k":[{"i":{"x":[0.833],"y":[0.833]},"o":{"x":[0.167],"y":[0.167]},"t":14,"s":[100],"e":[18]},{"t":52}],"ix":11},"r":{"a":0,"k":0,"ix":10},"p":{"a":0,"k":[372.5,371.5,0],"ix":2},"a":{"a":0,"k":[230,232,0],"ix":1},"s":{"a":1,"k":[{"i":{"x":[0.667,0.667,0.667],"y":[1,1,1]},"o":{"x":[0.333,0.333,0.333],"y":[0,0,0]},"t":14,"s":[84,84,100],"e":[111,111,100]},{"t":52}],"ix":6}},"ao":0,"ip":0,"op":53,"st":0,"bm":0},{"ddd":0,"ind":10,"ty":2,"nm":"9","refId":"image_7","sr":1,"ks":{"o":{"a":1,"k":[{"i":{"x":[0.833],"y":[0.833]},"o":{"x":[0.167],"y":[0.167]},"t":16,"s":[100],"e":[25]},{"t":54}],"ix":11},"r":{"a":0,"k":0,"ix":10},"p":{"a":0,"k":[372.5,371.5,0],"ix":2},"a":{"a":0,"k":[230,232,0],"ix":1},"s":{"a":1,"k":[{"i":{"x":[0.667,0.667,0.667],"y":[1,1,1]},"o":{"x":[0.333,0.333,0.333],"y":[0,0,0]},"t":16,"s":[92,92,100],"e":[123,123,100]},{"t":54}],"ix":6}},"ao":0,"ip":0,"op":53,"st":0,"bm":0},{"ddd":0,"ind":11,"ty":2,"nm":"10","refId":"image_7","sr":1,"ks":{"o":{"a":1,"k":[{"i":{"x":[0.833],"y":[0.833]},"o":{"x":[0.167],"y":[0.167]},"t":18,"s":[100],"e":[4]},{"t":54}],"ix":11},"r":{"a":0,"k":0,"ix":10},"p":{"a":0,"k":[372.5,371.5,0],"ix":2},"a":{"a":0,"k":[230,232,0],"ix":1},"s":{"a":1,"k":[{"i":{"x":[0.667,0.667,0.667],"y":[1,1,1]},"o":{"x":[0.333,0.333,0.333],"y":[0,0,0]},"t":18,"s":[101,101,100],"e":[132,132,100]},{"t":54}],"ix":6}},"ao":0,"ip":0,"op":53,"st":0,"bm":0},{"ddd":0,"ind":12,"ty":2,"nm":"11","refId":"image_7","sr":1,"ks":{"o":{"a":1,"k":[{"i":{"x":[0.833],"y":[0.833]},"o":{"x":[0.167],"y":[0.167]},"t":20,"s":[100],"e":[0]},{"t":54}],"ix":11},"r":{"a":0,"k":0,"ix":10},"p":{"a":0,"k":[372.5,371.5,0],"ix":2},"a":{"a":0,"k":[230,232,0],"ix":1},"s":{"a":1,"k":[{"i":{"x":[0.662,0.662,0.662],"y":[0.605,0.605,1.476]},"o":{"x":[0.296,0.296,0.296],"y":[0,0,0]},"t":20,"s":[109,109,100],"e":[131.725,131.725,100]},{"i":{"x":[0.709,0.709,0.709],"y":[0.604,0.604,1.024]},"o":{"x":[0.363,0.363,0.363],"y":[0.568,0.568,-0.279]},"t":42,"s":[131.725,131.725,100],"e":[141,141,100]},{"t":54}],"ix":6}},"ao":0,"ip":0,"op":53,"st":0,"bm":0}]}],"layers":[{"ddd":0,"ind":1,"ty":0,"nm":"预合成 1","refId":"comp_0","sr":1,"ks":{"o":{"a":0,"k":40,"ix":11},"r":{"a":0,"k":0,"ix":10},"p":{"a":0,"k":[340,340,0],"ix":2},"a":{"a":0,"k":[375,375,0],"ix":1},"s":{"a":0,"k":[100,100,100],"ix":6}},"ao":0,"hasMask":true,"masksProperties":[{"inv":false,"mode":"a","pt":{"a":0,"k":{"i":[[0,0],[0,0],[0,0],[0,0]],"o":[[0,0],[0,0],[0,0],[0,0]],"v":[[714,35],[35,35],[35,714],[714,714]],"c":true},"ix":1},"o":{"a":0,"k":100,"ix":3},"x":{"a":0,"k":0,"ix":4},"nm":"蒙版 1"}],"w":750,"h":750,"ip":0,"op":53,"st":0,"bm":0}],"markers":[]}